<?xml version="1.0" encoding="UTF-8"?>
<SAXEvents>
  <startDocument/>
  <startElement>
    <namespaceURI/>
    <localName>student</localName>
    <qualifiedName>student</qualifiedName>
    <attributes/>
  </startElement>
  <characters>M</characters>
  <characters>y</characters>
  <characters>&#x20;</characters>
  <characters>N</characters>
  <characters>a</characters>
  <characters>m</characters>
  <characters>e</characters>
  <characters>&#x20;</characters>
  <characters>i</characters>
  <characters>s</characters>
  <characters>&#x20;</characters>
  <characters>S</characters>
  <characters>n</characters>
  <characters>o</characters>
  <characters>w</characters>
  <characters>M</characters>
  <characters>a</characters>
  <characters>n</characters>
  <characters>.</characters>
  <characters>&#x20;</characters>
  <characters>T</characters>
  <characters>h</characters>
  <characters>i</characters>
  <characters>s</characters>
  <characters>&#x20;</characters>
  <characters>i</characters>
  <characters>s</characters>
  <characters>&#x20;</characters>
  <error>[XML&#x20;3&#x20;VC:&#x20;Element&#x20;Valid]&#x20;no&#x20;declaration&#x20;for&#x20;element</error>
  <startElement>
    <namespaceURI/>
    <localName>normal</localName>
    <qualifiedName>normal</qualifiedName>
    <attributes/>
  </startElement>
  <characters>&#x20;</characters>
  <characters>t</characters>
  <characters>e</characters>
  <characters>x</characters>
  <characters>t</characters>
  <fatalError>[[14]&#x20;CharData]&#x20;Text&#x20;may&#x20;not&#x20;contain&#x20;a&#x20;literal&#x20;&apos;]]&gt;&apos;&#x20;sequence</fatalError>
  <endDocument/>
</SAXEvents>
